example_pkg/__init__.py
classification_text_email-0.0.1.dist-info/LICENSE
classification_text_email-0.0.1.dist-info/METADATA
classification_text_email-0.0.1.dist-info/WHEEL
classification_text_email-0.0.1.dist-info/top_level.txt
classification_text_email-0.0.1.dist-info/RECORD
