Metadata-Version: 2.1
Name: classification-text-email
Version: 0.0.1
Summary: compiled packages
Home-page: https://github.com/pypa/sampleproject
Author: Ataul Karim Baig
Author-email: ataul.baig@exlservice.com
License: UNKNOWN
Platform: UNKNOWN
Classifier: Programming Language :: Python :: 3
Classifier: License :: OSI Approved :: MIT License
Classifier: Operating System :: OS Independent
Requires-Python: >=3.6
Requires-Dist: numpy (==1.17.3)
Requires-Dist: scikit-learn (==0.23.1)
Requires-Dist: spacy (==2.3.2)
Requires-Dist: autocorrect
Requires-Dist: lime
Requires-Dist: gensim (==3.4.0)
Requires-Dist: pyLDAvis (==2.1.2)
Requires-Dist: docx2pdf (==0.1.7)
Requires-Dist: python-docx (==0.8.10)
Requires-Dist: pyPDF2 (==1.26.0)
Requires-Dist: pywin32 (==227)
Requires-Dist: wordninja
Requires-Dist: nltk (==3.4.1)
Requires-Dist: pandas (==0.25.3)
Requires-Dist: tensorflow (==1.15.3)
Requires-Dist: tensorflow-gpu (==1.15.3)
Requires-Dist: tensorflow-hub (==0.7.0)
Requires-Dist: bert-tensorflow (==1.0.1)
Requires-Dist: keras (==2.2.4)
Requires-Dist: autoviml
Requires-Dist: typed-ast (>=1.3.0)
Requires-Dist: dask[complete]
Requires-Dist: requests (==2.22.0)
Requires-Dist: flask (==1.1.1)
Requires-Dist: joblib (==0.16.0)
Requires-Dist: dask-ml
Requires-Dist: bert-for-tf2
Requires-Dist: networkx
Requires-Dist: wordcloud
Requires-Dist: cntk
